TauLidarCamera/__init__.py
TauLidarCamera/__version__.py
TauLidarCamera/camera.py
TauLidarCamera/communication.py
TauLidarCamera/constants.py
TauLidarCamera/crc.py
TauLidarCamera/info.py
TauLidarCamera/util.py
TauLidarCamera-0.0.5.dist-info/LICENSE
TauLidarCamera-0.0.5.dist-info/METADATA
TauLidarCamera-0.0.5.dist-info/WHEEL
TauLidarCamera-0.0.5.dist-info/top_level.txt
TauLidarCamera-0.0.5.dist-info/RECORD
