Metadata-Version: 2.1
Name: TauLidarCamera
Version: 0.0.5
Summary: Python host-side API for the Onion Tau Lidar Camera
Home-page: https://github.com/OnionIoT/tau-lidar-camera
Author: Onion Corporation
Author-email: hello@onioniot.com
License: MIT
Platform: UNKNOWN
Classifier: Programming Language :: Python :: 3
Classifier: License :: OSI Approved :: MIT License
Classifier: Operating System :: OS Independent
Requires-Python: >=3.6.1
